PersonalExerciseTrainer/EX1.py
PersonalExerciseTrainer/EX2.py
PersonalExerciseTrainer/EX3.py
PersonalExerciseTrainer/EX4.py
PersonalExerciseTrainer/__init__.py
PersonalExerciseTrainer/Backend/Mediapipe_backend.py
PersonalExerciseTrainer/Backend/__init__.py
PersonalExerciseTrainer-1.0.8.dist-info/LICENCE
PersonalExerciseTrainer-1.0.8.dist-info/METADATA
PersonalExerciseTrainer-1.0.8.dist-info/WHEEL
PersonalExerciseTrainer-1.0.8.dist-info/top_level.txt
PersonalExerciseTrainer-1.0.8.dist-info/RECORD
