Metadata-Version: 2.1
Name: PersonalExerciseTrainer
Version: 1.0.8
Summary: This package will help users to create its own AI based exercise trainer
Home-page: https://www.besingular.com/
Author: BeSingular
Author-email: hitesh.gupta@besingular.com
License: MIT
Platform: UNKNOWN
Classifier: License :: OSI Approved :: MIT License
Classifier: Programming Language :: Python :: 3.7
Classifier: Programming Language :: Python :: 3.9
Requires-Python: >=3.7.9
Requires-Dist: mediapipe
Requires-Dist: pyautogui
Requires-Dist: opencv-python
